plut
