Metadata-Version: 1.1
Name: plut
Version: 0.5.2
Summary: port manager for developing multiple local web apps
Home-page: https://github.com/brhsiao/plut
Author: Brandon Hsiao
Author-email: bh@stoatlabs.com
License: MIT
Download-URL: https://github.com/brhsiao/plut/tarball/0.5.2
Platform: UNKNOWN
